pipreqsafe/__init__.py
pipreqsafe/cli.py
pipreqsafe/core.py
pipreqsafe-0.1.0.dist-info/METADATA
pipreqsafe-0.1.0.dist-info/WHEEL
pipreqsafe-0.1.0.dist-info/entry_points.txt
pipreqsafe-0.1.0.dist-info/top_level.txt
pipreqsafe-0.1.0.dist-info/RECORD
