Metadata-Version: 2.4
Name: pipreqsafe
Version: 0.1.0
Summary: Safely generate requirements.txt from pip list-style output
License: MIT
Requires-Python: >=3.8
